uamqp/__init__.py
uamqp/address.py
uamqp/c_uamqp.c
uamqp/c_uamqp.cp310-win_amd64.pyd
uamqp/client.py
uamqp/compat.py
uamqp/connection.py
uamqp/constants.py
uamqp/errors.py
uamqp/message.py
uamqp/mgmt_operation.py
uamqp/receiver.py
uamqp/sender.py
uamqp/session.py
uamqp/types.py
uamqp/utils.py
uamqp/async_ops/__init__.py
uamqp/async_ops/client_async.py
uamqp/async_ops/connection_async.py
uamqp/async_ops/mgmt_operation_async.py
uamqp/async_ops/receiver_async.py
uamqp/async_ops/sender_async.py
uamqp/async_ops/session_async.py
uamqp/async_ops/utils.py
uamqp/authentication/__init__.py
uamqp/authentication/cbs_auth.py
uamqp/authentication/cbs_auth_async.py
uamqp/authentication/common.py
uamqp-1.6.11.dist-info/LICENSE
uamqp-1.6.11.dist-info/METADATA
uamqp-1.6.11.dist-info/WHEEL
uamqp-1.6.11.dist-info/top_level.txt
uamqp-1.6.11.dist-info/RECORD
